{
  "title": "Pitiless Horde",
  "image": "../img/p/pitiless-horde.jpg",
  "convertedManaCost": "3",
  "types": "Creature  — Orc Berserker",
  "text": "At the beginning of your upkeep, you lose 2 life.Dash  (You may cast this spell for its dash cost. If you do, it gains haste, and it's returned from the battlefield to its owner's hand at the beginning of the next end step.)",
  "expansion": "Dragons of Tarkir",
  "rarity": "Rare",
  "cardNumber": "112",
  "artist": "Viktor Titov",
  "rating": "5",
  "votes": "0"
}