{
  "title": "Evolution Charm",
  "image": "../img/e/evolution-charm.jpg",
  "convertedManaCost": "2",
  "types": "Instant",
  "text": "Choose one —• Search your library for a basic land card, reveal it, put it into your hand, then shuffle your library.• Return target creature card from your graveyard to your hand.• Target creature gains flying until end of turn.",
  "expansion": "Planar Chaos",
  "rarity": "Common",
  "cardNumber": "127",
  "artist": "John Avon",
  "rating": "4.145",
  "votes": "76"
}