{
  "title": "Rohgahh of Kher Keep",
  "image": "../img/r/rohgahh-ofkherkeep.jpg",
  "convertedManaCost": "6",
  "types": "Legendary Creature  — Kobold",
  "text": "At the beginning of your upkeep, you may pay . If you don't, tap Rohgahh of Kher Keep and all creatures named Kobolds of Kher Keep, then an opponent gains control of them.Creatures you control named Kobolds of Kher Keep get +2/+2.",
  "expansion": "Masters Edition III",
  "rarity": "Rare",
  "cardNumber": "172",
  "artist": "Edward P. Beard, Jr.",
  "rating": "3.090",
  "votes": "50"
}