{
  "title": "Aurelia, the Warleader",
  "image": "./img/aurelia-thewarleader.jpg",
  "convertedManaCost": "6",
  "types": "Legendary Creature  — Angel",
  "text": "Flying, vigilance, hasteWhenever Aurelia, the Warleader attacks for the first time each turn, untap all creatures you control. After this phase, there is an additional combat phase.",
  "expansion": "From the Vault: Angels",
  "rarity": "Mythic Rare",
  "cardNumber": "4",
  "artist": "Slawomir Maniak",
  "rating": "5",
  "votes": "0"
}