{
  "title": "Emerge Unscathed",
  "image": "./img/emerge-unscathed.jpg",
  "convertedManaCost": "1",
  "types": "Instant",
  "text": "Target creature you control gains protection from the color of your choice until end of turn.Rebound (If you cast this spell from your hand, exile it as it resolves. At the beginning of your next upkeep, you may cast this card from exile without paying its mana cost.)",
  "expansion": "Rise of the Eldrazi",
  "rarity": "Uncommon",
  "cardNumber": "20",
  "artist": "Steve Argyle",
  "rating": "4.038",
  "votes": "78"
}