{
  "title": "Hankyu",
  "image": "./img/hankyu.jpg",
  "convertedManaCost": "1",
  "types": "Artifact  — Equipment",
  "text": "Equipped creature has \": Put an aim counter on Hankyu\" and \", Remove all aim counters from Hankyu: This creature deals damage to target creature or player equal to the number of aim counters removed this way.\"Equip  (: Attach to target creature you control. Equip only as a sorcery.)",
  "expansion": "Champions of Kamigawa",
  "rarity": "Uncommon",
  "cardNumber": "253",
  "artist": "Ben Thompson",
  "rating": "2.819",
  "votes": "47"
}