{
  "title": "Pharika, God of Affliction",
  "image": "./img/pharika-godofaffliction.jpg",
  "convertedManaCost": "3",
  "types": "Legendary Enchantment Creature  — God",
  "text": "IndestructibleAs long as your devotion to black and green is less than seven, Pharika isn't a creature.: Exile target creature card from a graveyard. Its owner puts a 1/1 black and green Snake enchantment creature token with deathtouch onto the battlefield.",
  "expansion": "Journey into Nyx",
  "rarity": "Mythic Rare",
  "cardNumber": "154",
  "artist": "Peter Mohrbacher",
  "rating": "3.373",
  "votes": "75"
}