{
  "title": "Raven Familiar",
  "image": "./img/raven-familiar.jpg",
  "convertedManaCost": "3",
  "types": "Creature  — Bird",
  "text": "FlyingEcho  (At the beginning of your upkeep, if this came under your control since the beginning of your last upkeep, sacrifice it unless you pay its echo cost.)When Raven Familiar enters the battlefield, look at the top three cards of your library. Put one of them into your hand and the rest on the bottom of your library in any order.",
  "expansion": "Commander 2013 Edition",
  "rarity": "Uncommon",
  "cardNumber": "55",
  "artist": "John Avon",
  "rating": "3.844",
  "votes": "16"
}