{
  "title": "Sands of Time",
  "image": "./img/sands-oftime.jpg",
  "convertedManaCost": "4",
  "types": "Artifact",
  "text": "Each player skips his or her untap step.At the beginning of each player's upkeep, that player simultaneously untaps each tapped artifact, creature, and land he or she controls and taps each untapped artifact, creature, and land he or she controls.",
  "expansion": "Visions",
  "rarity": "Rare",
  "cardNumber": "",
  "artist": "Paul Lee",
  "rating": "4.182",
  "votes": "44"
}