{
  "title": "Search the City",
  "image": "./img/search-thecity.jpg",
  "convertedManaCost": "5",
  "types": "Enchantment",
  "text": "When Search the City enters the battlefield, exile the top five cards of your library.Whenever you play a card with the same name as one of the exiled cards, you may put one of those cards with that name into its owner's hand. Then if there are no cards exiled with Search the City, sacrifice it. If you do, take an extra turn after this one.",
  "expansion": "Return to Ravnica",
  "rarity": "Rare",
  "cardNumber": "49",
  "artist": "Jack Wang",
  "rating": "2.123",
  "votes": "73"
}