{
  "title": "Shrine of Loyal Legions",
  "image": "./img/shrine-ofloyallegions.jpg",
  "convertedManaCost": "2",
  "types": "Artifact",
  "text": "At the beginning of your upkeep or whenever you cast a white spell, put a charge counter on Shrine of Loyal Legions., , Sacrifice Shrine of Loyal Legions: Put a 1/1 colorless Myr artifact creature token onto the battlefield for each charge counter on Shrine of Loyal Legions.",
  "expansion": "Modern Event Deck 2014",
  "rarity": "Uncommon",
  "cardNumber": "5",
  "artist": "Igor Kieryluk",
  "rating": "3.167",
  "votes": "9"
}