{
  "title": "Svogthos, the Restless Tomb",
  "image": "./img/svogthos-therestlesstomb.jpg",
  "convertedManaCost": "",
  "types": "Land",
  "text": ": Add  to your mana pool.: Until end of turn, Svogthos, the Restless Tomb becomes a black and green Plant Zombie creature with \"This creature's power and toughness are each equal to the number of creature cards in your graveyard.\" It's still a land.",
  "expansion": "Duel Decks: Izzet vs. Golgari",
  "rarity": "Uncommon",
  "cardNumber": "81",
  "artist": "Martina Pilcerova",
  "rating": "3.886",
  "votes": "22"
}