{
  "title": "Thawing Glaciers",
  "image": "./img/thawing-glaciers.jpg",
  "convertedManaCost": "",
  "types": "Land",
  "text": "Thawing Glaciers enters the battlefield tapped., : Search your library for a basic land card, put that card onto the battlefield tapped, then shuffle your library. Return Thawing Glaciers to its owner's hand at the beginning of the next cleanup step.",
  "expansion": "Vintage Masters",
  "rarity": "Rare",
  "cardNumber": "318",
  "artist": "Jim Nelson",
  "rating": "4.000",
  "votes": "1"
}