{
  "title": "Thran Weaponry",
  "image": "./img/thran-weaponry.jpg",
  "convertedManaCost": "4",
  "types": "Artifact",
  "text": "Echo  (At the beginning of your upkeep, if this came under your control since the beginning of your last upkeep, sacrifice it unless you pay its echo cost.)You may choose not to untap Thran Weaponry during your untap step., : All creatures get +2/+2 for as long as Thran Weaponry remains tapped.",
  "expansion": "Urza's Legacy",
  "rarity": "Rare",
  "cardNumber": "135",
  "artist": "Anthony S. Waters",
  "rating": "2.907",
  "votes": "27"
}