{
  "title": "Twilight Drover",
  "image": "./img/twilight-drover.jpg",
  "convertedManaCost": "3",
  "types": "Creature  — Spirit",
  "text": "Whenever a creature token leaves the battlefield, put a +1/+1 counter on Twilight Drover., Remove a +1/+1 counter from Twilight Drover: Put two 1/1 white Spirit creature tokens with flying onto the battlefield.",
  "expansion": "Duel Decks: Sorin vs. Tibalt",
  "rarity": "Rare",
  "cardNumber": "9",
  "artist": "Dave Allsop",
  "rating": "3.529",
  "votes": "17"
}