{
  "title": "White Knight",
  "image": "./img/white-knight.jpg",
  "convertedManaCost": "2",
  "types": "Creature  — Human Knight",
  "text": "First strike (This creature deals combat damage before creatures without first strike.)Protection from black (This creature can't be blocked, targeted, dealt damage, or enchanted by anything black.)",
  "expansion": "Duel Decks: Knights vs. Dragons",
  "rarity": "Uncommon",
  "cardNumber": "9",
  "artist": "Christopher Moeller",
  "rating": "4.277",
  "votes": "56"
}